qpimage/__init__.py
qpimage/_version.py
qpimage/bg_estimate.py
qpimage/core.py
qpimage/image_data.py
qpimage/integrity_check.py
qpimage/meta.py
qpimage/series.py
qpimage-0.9.3.dist-info/LICENSE
qpimage-0.9.3.dist-info/METADATA
qpimage-0.9.3.dist-info/WHEEL
qpimage-0.9.3.dist-info/top_level.txt
qpimage-0.9.3.dist-info/RECORD
