Metadata-Version: 2.2
Name: qpimage
Version: 0.9.3
Summary: library for manipulating quantitative phase images
Author-email: Paul Müller <dev@craban.de>
License: MIT License
Project-URL: Homepage, https://github.com/RI-imaging/qpimage
Classifier: Operating System :: OS Independent
Classifier: Programming Language :: Python :: 3
Classifier: Intended Audience :: Science/Research
Requires-Python: <4,>=3.8
License-File: LICENSE
Requires-Dist: h5py>=2.7.0
Requires-Dist: lmfit
Requires-Dist: nrefocus[FFTW]>=0.4.3
Requires-Dist: numpy>=2.0
Requires-Dist: qpretrieve[FFTW]>=0.2.8
Requires-Dist: scikit-image>=0.21.0
Requires-Dist: scipy>=0.18.0
